{"blog_name":"reallysmall","id":24210686584,"post_url":"http://reallysmall.tumblr.com/post/24210686584/yellow-flag-iris-vivitar-series-1-90mm-macro","slug":"yellow-flag-iris-vivitar-series-1-90mm-macro","type":"photo","date":"2012-06-01 20:06:33 GMT","timestamp":1338581193,"state":"published","format":"html","reblog_key":"MmYei1HH","tags":["Yellow","Iris","Flower","Close up","Vivitar Series 1"],"short_url":"http://tmblr.co/ZNs_txMZ4S9u","summary":"Yellow Flag Iris\r\n Vivitar Series 1 90mm Macro","recommended_source":null,"recommended_color":null,"highlighted":[],"note_count":1,"caption":"<p><strong>Yellow Flag Iris</strong></p>\n<p>Vivitar Series 1 90mm Macro</p>","reblog":{"tree_html":"","comment":"<p><strong>Yellow Flag Iris</strong></p>\n<p>Vivitar Series 1 90mm Macro</p>"},"trail":[{"blog":{"name":"reallysmall","active":true,"theme":{"avatar_shape":"square","background_color":"#FAFAFA","body_font":"Helvetica Neue","header_bounds":"","header_image":"https://secure.assets.tumblr.com/images/default_header/optica_pattern_04.png?_v=7c4e5e82cf797042596e2e64af1c383f","header_image_focused":"https://secure.assets.tumblr.com/images/default_header/optica_pattern_04_focused_v3.png?_v=7c4e5e82cf797042596e2e64af1c383f","header_image_scaled":"https://secure.assets.tumblr.com/images/default_header/optica_pattern_04_focused_v3.png?_v=7c4e5e82cf797042596e2e64af1c383f","header_stretch":true,"link_color":"#529ECC","show_avatar":true,"show_description":true,"show_header_image":true,"show_title":true,"title_color":"#444444","title_font":"Gibson","title_font_weight":"bold"}},"post":{"id":"24210686584"},"content_raw":"<p><strong>Yellow Flag Iris</strong></p>\n<p>Vivitar Series 1 90mm Macro</p>","content":"<p><strong>Yellow Flag Iris</strong></p>\n<p>Vivitar Series 1 90mm Macro</p>","is_current_item":true,"is_root_item":true}],"image_permalink":"http://reallysmall.tumblr.com/image/24210686584","photos":[{"caption":"","alt_sizes":[{"url":"http://40.media.tumblr.com/tumblr_m4yfuxa3bw1qgnzwco1_1280.jpg","width":800,"height":1200},{"url":"http://41.media.tumblr.com/tumblr_m4yfuxa3bw1qgnzwco1_500.jpg","width":500,"height":750},{"url":"http://40.media.tumblr.com/tumblr_m4yfuxa3bw1qgnzwco1_400.jpg","width":400,"height":600},{"url":"http://41.media.tumblr.com/tumblr_m4yfuxa3bw1qgnzwco1_250.jpg","width":250,"height":375},{"url":"http://40.media.tumblr.com/tumblr_m4yfuxa3bw1qgnzwco1_100.jpg","width":100,"height":150},{"url":"http://40.media.tumblr.com/tumblr_m4yfuxa3bw1qgnzwco1_75sq.jpg","width":75,"height":75}],"original_size":{"url":"http://40.media.tumblr.com/tumblr_m4yfuxa3bw1qgnzwco1_1280.jpg","width":800,"height":1200}}]}